MANIFEST.in
README.rst
setup.py
poolbase/__init__.py
poolbase/connection.py
poolbase/pool.py
poolbase.egg-info/PKG-INFO
poolbase.egg-info/SOURCES.txt
poolbase.egg-info/dependency_links.txt
poolbase.egg-info/top_level.txt