Metadata-Version: 1.1
Name: poolbase
Version: 0.1.1
Summary: A connection pool for anything
Home-page: https://github.com/duanhongyi/poolbase
Author: duanhongyi
Author-email: duanhongyi@doopai.com
License: MIT
Platform: UNKNOWN
Classifier: License :: OSI Approved :: MIT License
Classifier: Topic :: Database
Classifier: Topic :: Software Development :: Libraries :: Python Modules
